imgdownloader/__init__.py
imgdownloader-1.2.dist-info/LICENSE.txt
imgdownloader-1.2.dist-info/METADATA
imgdownloader-1.2.dist-info/WHEEL
imgdownloader-1.2.dist-info/top_level.txt
imgdownloader-1.2.dist-info/RECORD
