Metadata-Version: 2.1
Name: imgdownloader
Version: 1.2
Summary: Use this library to download any image from a given URL.
Home-page: https://github.com/Ankit404butfound/pydownimg
Author: Ankit Raj Mahapatra
Author-email: ankitrajjitendra816@gmail.com
License: MIT
Download-URL: https://github.com/Ankit404butfound/pydownimg
Keywords: download
Platform: UNKNOWN
Classifier: Development Status :: 3 - Alpha
Classifier: Intended Audience :: Developers
Classifier: Topic :: Software Development :: Build Tools
Classifier: License :: OSI Approved :: MIT License
Classifier: Programming Language :: Python :: 3
Classifier: Programming Language :: Python :: 3.4
Classifier: Programming Language :: Python :: 3.5
Classifier: Programming Language :: Python :: 3.6
Requires-Dist: opencv-python
Requires-Dist: numpy
